happiness1/__init__.py
happiness1/main.py
happiness1-1.0.0.dist-info/licenses/LICENSE
happiness1-1.0.0.dist-info/METADATA
happiness1-1.0.0.dist-info/WHEEL
happiness1-1.0.0.dist-info/entry_points.txt
happiness1-1.0.0.dist-info/top_level.txt
happiness1-1.0.0.dist-info/RECORD
